synthora/__init__.py
synthora/agents/__init__.py
synthora/agents/base.py
synthora/agents/react_agent.py
synthora/agents/tot_agent.py
synthora/agents/vanilla_agent.py
synthora/callbacks/__init__.py
synthora/callbacks/base_handler.py
synthora/callbacks/base_manager.py
synthora/callbacks/output_handler.py
synthora/callbacks/rich_output_handler.py
synthora/code_automations/__init__.py
synthora/code_automations/graph.py
synthora/code_automations/agents/agents.py
synthora/code_automations/agents/prompts.py
synthora/code_automations/blocks/__init__.py
synthora/code_automations/blocks/base.py
synthora/code_automations/blocks/code_block.py
synthora/code_automations/blocks/condition_block.py
synthora/code_automations/blocks/input_block.py
synthora/code_automations/blocks/loop_block.py
synthora/configs/__init__.py
synthora/configs/agent_config.py
synthora/configs/base.py
synthora/configs/model_config.py
synthora/configs/tool_config.py
synthora/memories/__init__.py
synthora/memories/base.py
synthora/memories/full_context_memory.py
synthora/memories/recent_n_memory.py
synthora/memories/summary_memory.py
synthora/messages/__init__.py
synthora/messages/base.py
synthora/models/__init__.py
synthora/models/azure_chat.py
synthora/models/azure_completion.py
synthora/models/base.py
synthora/models/openai_chat.py
synthora/models/openai_completion.py
synthora/prompts/__init__.py
synthora/prompts/base.py
synthora/prompts/buildin/__init__.py
synthora/prompts/buildin/cot.py
synthora/prompts/buildin/react.py
synthora/prompts/buildin/tot.py
synthora/prompts/buildin/vanilla.py
synthora/services/__init__.py
synthora/services/base.py
synthora/services/discord_bot.py
synthora/services/http_service.py
synthora/services/slack_bot.py
synthora/toolkits/__init__.py
synthora/toolkits/base.py
synthora/toolkits/basic_math_toolkit.py
synthora/toolkits/decorators.py
synthora/toolkits/file_toolkit.py
synthora/toolkits/finance.py
synthora/toolkits/news.py
synthora/toolkits/search_toolkit.py
synthora-0.1.15.dist-info/METADATA
synthora-0.1.15.dist-info/WHEEL
synthora-0.1.15.dist-info/licenses/LICENSE
synthora-0.1.15.dist-info/RECORD
