Metadata-Version: 2.4
Name: synthora
Version: 0.1.15
Summary: Synthora is a lightweight and extensible framework for LLM-driven Agents and ALM research. It provides essential components to build, test and evaluate agents. At its core, Synthora aims to assemble an agent with a single config, thus minimizing your effort in building, tuning, and sharing agents.
Author: Syntropix.AI
License-File: LICENSE
Requires-Python: ~=3.10
Requires-Dist: apscheduler<4,>=3.11.0
Requires-Dist: asyncio<4,>=3.4.3
Requires-Dist: docstring-parser<0.17,>=0.16
Requires-Dist: fastapi<0.116,>=0.115.5
Requires-Dist: openai<2,>=1.55.0
Requires-Dist: pydantic<3,>=2.10.1
Requires-Dist: python-dotenv<2,>=1.0.1
Requires-Dist: pyyaml<7,>=6.0.2
Requires-Dist: rich<14,>=13.9.4
Requires-Dist: websockets~=14.1
Provides-Extra: services
Requires-Dist: discord-py<3,>=2.4.0; extra == 'services'
Requires-Dist: slack-bolt<2,>=1.22.0; extra == 'services'
Provides-Extra: toolkits
Requires-Dist: googlesearch-python<2,>=1.2.5; extra == 'toolkits'
Requires-Dist: pymediawiki<0.8,>=0.7.5; extra == 'toolkits'
Requires-Dist: trafilatura<3,>=2.0.0; extra == 'toolkits'
Requires-Dist: wikipedia<2,>=1.4.0; extra == 'toolkits'
